{
"type": "FeatureCollection",
"name": "figure-2",
"crs": { "type": "name", "properties": { "name": "urn:ogc:def:crs:OGC:1.3:CRS84" } },
"features": [
{ "type": "Feature", "properties": { "type": "borehole", "elevation": 3830 }, "geometry": { "type": "Point", "coordinates": [ 71.565324, 39.649074 ] } },
{ "type": "Feature", "properties": { "type": "borehole", "elevation": 4070 }, "geometry": { "type": "Point", "coordinates": [ 71.558589, 39.624305 ] } },
{ "type": "Feature", "properties": { "type": "borehole", "elevation": 4250 }, "geometry": { "type": "Point", "coordinates": [ 71.566285, 39.603198 ] } }
]
}
