{
"type": "FeatureCollection",
"name": "location",
"crs": { "type": "name", "properties": { "name": "urn:ogc:def:crs:OGC:1.3:CRS84" } },
"features": [
{ "type": "Feature", "properties": { "label": "4800 m" }, "geometry": { "type": "Point", "coordinates": [ 6.867093, 45.832639 ] } },
{ "type": "Feature", "properties": { "label": "4250 m" }, "geometry": { "type": "Point", "coordinates": [ 6.850262, 45.838716 ] } },
{ "type": "Feature", "properties": { "label": "3960 m" }, "geometry": { "type": "Point", "coordinates": [ 6.860465, 45.844536 ] } }
]
}
