{
"type": "FeatureCollection",
"name": "location",
"crs": { "type": "name", "properties": { "name": "urn:ogc:def:crs:OGC:1.3:CRS84" } },
"features": [
{ "type": "Feature", "properties": { "label": "camp" }, "geometry": { "type": "Point", "coordinates": [ 24.17342, 79.83728 ] } },
{ "type": "Feature", "properties": { "label": "3" }, "geometry": { "type": "Point", "coordinates": [ 23.82282, 79.86612 ] } },
{ "type": "Feature", "properties": { "label": "4" }, "geometry": { "type": "Point", "coordinates": [ 24.0863, 79.85863 ] } },
{ "type": "Feature", "properties": { "label": "5" }, "geometry": { "type": "Point", "coordinates": [ 24.61963, 79.79821 ] } },
{ "type": "Feature", "properties": { "label": "6" }, "geometry": { "type": "Point", "coordinates": [ 24.87248, 79.77673 ] } },
{ "type": "Feature", "properties": { "label": "7" }, "geometry": { "type": "Point", "coordinates": [ 25.08921, 79.75899 ] } },
{ "type": "Feature", "properties": { "label": "8" }, "geometry": { "type": "Point", "coordinates": [ 25.31231, 79.73705 ] } },
{ "type": "Feature", "properties": { "label": "2" }, "geometry": { "type": "Point", "coordinates": [ 24.1689, 79.82232 ] } }
]
}
